<annotation>
  <folder>data</folder>
  <filename>60GTS_dingxi_QC165536_1616k+574m_J</filename>
  <path>E:\data\60GTS_dingxi_QC165536_1616k+574m_J.jpg</path>
  <source>
    <database>Unknown</database>
  </source>
  <size>
    <width>800</width>
    <height>400</height>
    <depth>3</depth>
  </size>
  <segmented>0</segmented>
  <object>
    <name>J</name>
    <pose>Unspecified</pose>
    <truncated>0</truncated>
    <difficult>0</difficult>
    <bndbox>
      <xmin>385</xmin>
      <ymin>1</ymin>
      <xmax>424</xmax>
      <ymax>65</ymax>
    </bndbox>
  </object>
  <object>
    <name>y_p</name>
    <pose>Unspecified</pose>
    <truncated>0</truncated>
    <difficult>0</difficult>
    <bndbox>
      <xmin>223</xmin>
      <ymin>107</ymin>
      <xmax>582</xmax>
      <ymax>279</ymax>
    </bndbox>
  </object>
</annotation>
